examples/__init__.py
third_party/__init__.py
third_party/rtde/__init__.py
third_party/rtde/csv_binary_writer.py
third_party/rtde/csv_reader.py
third_party/rtde/csv_writer.py
third_party/rtde/record.py
third_party/rtde/rtde.py
third_party/rtde/rtde_config.py
third_party/rtde/serialize.py
urinterface/__init__.py
urinterface/recording.py
urinterface/robot_connection.py
urinterface-0.0.5.dist-info/LICENSE
urinterface-0.0.5.dist-info/METADATA
urinterface-0.0.5.dist-info/WHEEL
urinterface-0.0.5.dist-info/top_level.txt
urinterface-0.0.5.dist-info/RECORD
