Metadata-Version: 2.1
Name: urinterface
Version: 0.0.5
Summary: UR Robot Interface
Home-page: https://gitlab.au.dk/clagms/urinterface
Author: Claudio Gomes and Emil Madsen
Author-email: claudio.gomes@eng.au.dk
License: INTOCPS
Keywords: python,ur robot,universal robot
Platform: UNKNOWN
Classifier: Development Status :: 4 - Beta
Classifier: Intended Audience :: Developers
Classifier: License :: OSI Approved :: MIT License
Classifier: Programming Language :: Python
Classifier: Programming Language :: Python :: 3
Classifier: Programming Language :: Python :: 3 :: Only
Classifier: Programming Language :: Python :: 3.6
Classifier: Programming Language :: Python :: 3.7
Classifier: Programming Language :: Python :: 3.8
